betastr.py
betastr-0.7.1.dist-info/entry_points.txt
betastr-0.7.1.dist-info/licenses/LICENSE
betastr-0.7.1.dist-info/WHEEL
betastr-0.7.1.dist-info/METADATA
betastr-0.7.1.dist-info/RECORD
