Metadata-Version: 2.4
Name: betastr
Version: 0.7.1
Summary: betastr is a string rewriting system
Author-email: Kimmo Koskenniemi <koskenni@gmail.com>
Maintainer-email: Kimmo Koskenniemi <koskenni@gmail.com>
Requires-Python: >= 3.8
License-Expression: GPL-3.0-or-later
License-File: LICENSE
Requires-Dist: pygtrie >= 2.5
Project-URL: Home, https://github.com/koskenni/beta
